policyengine_data/__init__.py
policyengine_data/data_download_upload.py
policyengine_data/dataset_legacy.py
policyengine_data/multi_year_dataset.py
policyengine_data/normalise_keys.py
policyengine_data/single_year_dataset.py
policyengine_data/calibration/__init__.py
policyengine_data/calibration/calibrate.py
policyengine_data/calibration/dataset_duplication.py
policyengine_data/calibration/metrics_matrix_creation.py
policyengine_data/calibration/target_rescaling.py
policyengine_data/calibration/target_uprating.py
policyengine_data/calibration/utils.py
policyengine_data/tools/__init__.py
policyengine_data/tools/hugging_face.py
policyengine_data/tools/legacy_class_conversions.py
policyengine_data/tools/win_file_manager.py
policyengine_data-0.5.0.dist-info/METADATA
policyengine_data-0.5.0.dist-info/WHEEL
policyengine_data-0.5.0.dist-info/entry_points.txt
policyengine_data-0.5.0.dist-info/licenses/LICENSE
policyengine_data-0.5.0.dist-info/RECORD
