Metadata-Version: 2.4
Name: policyengine-data
Version: 0.5.0
Summary: A package to create representative microdata for PolicyEngine's policy models.
Author-email: PolicyEngine <hello@policyengine.org>
License-File: LICENSE
Requires-Python: >=3.11
Requires-Dist: h5py
Requires-Dist: huggingface-hub>=0.25.1
Requires-Dist: microcalibrate
Requires-Dist: microdf-python
Requires-Dist: numpy
Requires-Dist: pandas
Requires-Dist: policyengine-core>=3.6.4
Requires-Dist: policyengine-us
Requires-Dist: sqlalchemy
Requires-Dist: tables
Requires-Dist: torch
Provides-Extra: dev
Requires-Dist: black; extra == 'dev'
Requires-Dist: build; extra == 'dev'
Requires-Dist: flake8; extra == 'dev'
Requires-Dist: isort; extra == 'dev'
Requires-Dist: linecheck; extra == 'dev'
Requires-Dist: mypy; extra == 'dev'
Requires-Dist: policyengine-us>=1.366.0; extra == 'dev'
Requires-Dist: pytest; extra == 'dev'
Requires-Dist: pytest-cov; extra == 'dev'
Requires-Dist: yaml-changelog>=0.1.7; extra == 'dev'
Provides-Extra: docs
Requires-Dist: docutils>=0.17.0; extra == 'docs'
Requires-Dist: furo>=2022.12.7; extra == 'docs'
Requires-Dist: h5py<4.0.0,>=3.1.0; extra == 'docs'
Requires-Dist: ipywidgets>=7.8.0; extra == 'docs'
Requires-Dist: jupyter-book>=0.15.0; extra == 'docs'
Requires-Dist: myst-nb>=0.17.2; extra == 'docs'
Requires-Dist: myst-parser>=0.18.1; extra == 'docs'
Requires-Dist: plotly; extra == 'docs'
Requires-Dist: policyengine-core; extra == 'docs'
Requires-Dist: policyengine-us; extra == 'docs'
Requires-Dist: policyengine-us-data; extra == 'docs'
Requires-Dist: pyyaml; extra == 'docs'
Requires-Dist: sphinx-argparse>=0.5.0; extra == 'docs'
Requires-Dist: sphinx-book-theme>=1.0.0; extra == 'docs'
Requires-Dist: sphinx-copybutton>=0.5.0; extra == 'docs'
Requires-Dist: sphinx-design>=0.5.0; extra == 'docs'
Requires-Dist: sphinx-math-dollar>=1.2.1; extra == 'docs'
Requires-Dist: sphinx>=5.0.0; extra == 'docs'
